illustris/__init__.py
illustris/cartesian.py
illustris/cli.py
illustris/groupcat.py
illustris/lhalotree.py
illustris/py.typed
illustris/snapshot.py
illustris/sublink.py
illustris/util.py
illustris-0.1.0.dist-info/METADATA
illustris-0.1.0.dist-info/WHEEL
illustris-0.1.0.dist-info/entry_points.txt
illustris-0.1.0.dist-info/licenses/LICENSE.md
illustris-0.1.0.dist-info/RECORD
