Metadata-Version: 2.4
Name: illustris
Version: 0.1.0
Summary: Python tools for accessing and analyzing Illustris simulation data
Project-URL: Homepage, https://www.illustris-project.org/
Project-URL: Documentation, https://your-docs-url.com
Project-URL: Repository, https://github.com/bjoernbethge/illustris
Project-URL: Issues, https://github.com/bjoernbethge/illustris/issues
Project-URL: Changelog, https://github.com/bjoernbethge/illustris/releases
Author-email: Björn Bethge <bjoern.bethge@gmail.com>
Maintainer-email: Björn Bethge <bjoern.bethge@gmail.com>
License: Copyright (c) 2017, illustris & illustris_python developers
License-File: LICENSE.md
Keywords: astronomy,astrophysics,cosmology,illustris,simulation
Classifier: Development Status :: 4 - Beta
Classifier: Intended Audience :: Science/Research
Classifier: License :: OSI Approved :: MIT License
Classifier: Operating System :: OS Independent
Classifier: Programming Language :: Python :: 3
Classifier: Programming Language :: Python :: 3.11
Classifier: Programming Language :: Python :: 3.12
Classifier: Programming Language :: Python :: 3.13
Classifier: Topic :: Scientific/Engineering :: Astronomy
Classifier: Topic :: Scientific/Engineering :: Physics
Requires-Python: >=3.11
Requires-Dist: h5py>=3.14.0
Requires-Dist: httpx>=0.28.1
Requires-Dist: numpy>=2.2.6
Requires-Dist: python-dotenv>=1.0.0
Requires-Dist: six>=1.17.0
